README.md
pytest_sqlalchemy.py
setup.py
pytest_sqlalchemy.egg-info/PKG-INFO
pytest_sqlalchemy.egg-info/SOURCES.txt
pytest_sqlalchemy.egg-info/dependency_links.txt
pytest_sqlalchemy.egg-info/entry_points.txt
pytest_sqlalchemy.egg-info/requires.txt
pytest_sqlalchemy.egg-info/top_level.txt