Metadata-Version: 1.1
Name: pytest-sqlalchemy
Version: 0.2.0
Summary: pytest plugin with sqlalchemy related fixtures
Home-page: http://github.com/toirl/pytest-sqlalchemy/
Author: Torsten Irländer
Author-email: torsten.irlaender@googlemail.com
License: MIT
Platform: UNKNOWN
Classifier: Development Status :: 3 - Alpha
Classifier: Topic :: Software Development :: Testing
Classifier: Intended Audience :: Developers
Classifier: Operating System :: OS Independent
